dirsearch/CHANGELOG.md
dirsearch/CONTRIBUTORS.md
dirsearch/Dockerfile
dirsearch/README.md
dirsearch/__init__.py
dirsearch/config.ini
dirsearch/dirsearch.py
dirsearch/options.ini
dirsearch/requirements.txt
dirsearch/setup.cfg
dirsearch/setup.py
dirsearch/testing.py
dirsearch/db/400_blacklist.txt
dirsearch/db/403_blacklist.txt
dirsearch/db/500_blacklist.txt
dirsearch/db/dicc.txt
dirsearch/db/user-agents.txt
dirsearch/lib/__init__.py
dirsearch/lib/connection/__init__.py
dirsearch/lib/connection/dns.py
dirsearch/lib/connection/requester.py
dirsearch/lib/connection/response.py
dirsearch/lib/controller/__init__.py
dirsearch/lib/controller/controller.py
dirsearch/lib/core/__init__.py
dirsearch/lib/core/data.py
dirsearch/lib/core/decorators.py
dirsearch/lib/core/dictionary.py
dirsearch/lib/core/exceptions.py
dirsearch/lib/core/fuzzer.py
dirsearch/lib/core/installation.py
dirsearch/lib/core/logger.py
dirsearch/lib/core/options.py
dirsearch/lib/core/scanner.py
dirsearch/lib/core/settings.py
dirsearch/lib/core/structures.py
dirsearch/lib/parse/__init__.py
dirsearch/lib/parse/cmdline.py
dirsearch/lib/parse/config.py
dirsearch/lib/parse/headers.py
dirsearch/lib/parse/rawrequest.py
dirsearch/lib/parse/url.py
dirsearch/lib/reports/__init__.py
dirsearch/lib/reports/base.py
dirsearch/lib/reports/csv_report.py
dirsearch/lib/reports/html_report.py
dirsearch/lib/reports/json_report.py
dirsearch/lib/reports/markdown_report.py
dirsearch/lib/reports/plain_text_report.py
dirsearch/lib/reports/simple_report.py
dirsearch/lib/reports/sqlite_report.py
dirsearch/lib/reports/xml_report.py
dirsearch/lib/utils/__init__.py
dirsearch/lib/utils/common.py
dirsearch/lib/utils/crawl.py
dirsearch/lib/utils/diff.py
dirsearch/lib/utils/file.py
dirsearch/lib/utils/mimetype.py
dirsearch/lib/utils/pickle.py
dirsearch/lib/utils/random.py
dirsearch/lib/utils/schemedet.py
dirsearch/lib/view/__init__.py
dirsearch/lib/view/colors.py
dirsearch/lib/view/terminal.py
dirsearch/tests/__init__.py
dirsearch-0.4.3.post1.dist-info/METADATA
dirsearch-0.4.3.post1.dist-info/WHEEL
dirsearch-0.4.3.post1.dist-info/entry_points.txt
dirsearch-0.4.3.post1.dist-info/top_level.txt
dirsearch-0.4.3.post1.dist-info/RECORD
