Metadata-Version: 2.1
Name: dirsearch
Version: 0.4.3.post1
Summary: Advanced web path scanner
Home-page: https://github.com/maurosoria/dirsearch
Author: Mauro Soria
Author-email: maurosoria@protonmail.com
License: UNKNOWN
Keywords: infosec,bug bounty,pentesting,security
Platform: UNKNOWN
Classifier: Programming Language :: Python
Classifier: Environment :: Console
Classifier: Intended Audience :: Information Technology
Classifier: License :: OSI Approved :: GNU General Public License v2 (GPLv2)
Classifier: Operating System :: OS Independent
Classifier: Topic :: Security
Classifier: Programming Language :: Python :: 3.7
Requires-Python: >=3.7
